mist_statinf/__init__.py
mist_statinf/cli.py
mist_statinf/quickstart.py
mist_statinf/configs/data_generation/test_imd.yaml
mist_statinf/configs/data_generation/test_oomd.yaml
mist_statinf/configs/data_generation/train.yaml
mist_statinf/configs/data_generation/validation.yaml
mist_statinf/configs/inference/baselines.yaml
mist_statinf/configs/inference/mist_inference.yaml
mist_statinf/configs/inference/quickstart.yaml
mist_statinf/configs/train/mist_train.yaml
mist_statinf/data/__init__.py
mist_statinf/data/analysis_utils.py
mist_statinf/data/distribution_generator.py
mist_statinf/data/generate.py
mist_statinf/data/meta_dataloader.py
mist_statinf/data/meta_dataset.py
mist_statinf/data/multiadditive_noise.py
mist_statinf/infer/__init__.py
mist_statinf/infer/inference.py
mist_statinf/model/__init__.py
mist_statinf/model/architecture.py
mist_statinf/model/estimator.py
mist_statinf/model/losses.py
mist_statinf/model/modeling_hf.py
mist_statinf/train/baselines.py
mist_statinf/train/hparams_search.py
mist_statinf/train/lit_module.py
mist_statinf/train/train.py
mist_statinf/utils/__init__.py
mist_statinf/utils/bootstrap.py
mist_statinf/utils/device.py
mist_statinf/utils/downloads.py
mist_statinf/utils/format.py
mist_statinf/utils/io.py
mist_statinf/utils/logging.py
mist_statinf/utils/set_seed.py
mist_statinf-0.1.1.dist-info/licenses/LICENSE
mist_statinf-0.1.1.dist-info/METADATA
mist_statinf-0.1.1.dist-info/WHEEL
mist_statinf-0.1.1.dist-info/entry_points.txt
mist_statinf-0.1.1.dist-info/top_level.txt
mist_statinf-0.1.1.dist-info/RECORD
