Metadata-Version: 2.4
Name: mist-statinf
Version: 0.1.1
Summary: Neural mutual information estimators with quantile-based uncertainty
Author-email: German Gritsai <gritsai.gm@gmail.com>, Megan Richards <mr7401@nyu.edu>, Maxime Meloux <melouxm@univ-grenoble-alpes.fr>, Kyunghyun Cho <kyunghyun.cho@nyu.edu>, Maxime Peyrard <peyrardm@univ-grenoble-alpes.fr>
License: MIT License
Keywords: mutual-information,transformer,deep-learning,information-theory,uncertainty,statistical-inference
Requires-Python: >=3.9
License-File: LICENSE
Requires-Dist: torch>=2.2
Requires-Dist: numpy>=1.23
Requires-Dist: scipy>=1.10
Requires-Dist: tqdm>=4.65
Requires-Dist: pyyaml>=6.0
Requires-Dist: omegaconf>=2.3
Requires-Dist: typer>=0.9
Requires-Dist: matplotlib>=3.7
Requires-Dist: scikit-learn>=1.2
Requires-Dist: pandas>=1.5
Requires-Dist: pytorch-lightning>=2.3
Requires-Dist: torchmetrics>=1.4
Requires-Dist: benchmark-mi>=0.1.3
Requires-Dist: jsonlines>=4.0.0
Requires-Dist: seaborn>=0.13.2
Requires-Dist: jax==0.4.26
Requires-Dist: jaxlib==0.4.26
Requires-Dist: optuna>=4.6.0
Requires-Dist: huggingface-hub==0.36.0
Provides-Extra: jax
Requires-Dist: equinox>=0.10; extra == "jax"
Requires-Dist: jaxtyping>=0.3; extra == "jax"
Requires-Dist: optax>=0.1.9; extra == "jax"
Dynamic: license-file
